tensorset/__init__.py
tensorset/tensorset.py
tensorset/tests/__init__.py
tensorset/tests/test_tensorset.py
tensorset-0.4.5.dist-info/METADATA
tensorset-0.4.5.dist-info/WHEEL
tensorset-0.4.5.dist-info/top_level.txt
tensorset-0.4.5.dist-info/RECORD
