Metadata-Version: 2.4
Name: tensorset
Version: 0.4.5
Summary: manipulate sets of tensors
Home-page: https://github.com/theAdamColton/tensorset
Author: Adam Colton
Requires-Dist: torch>=2.0.1
Dynamic: author
Dynamic: description
Dynamic: description-content-type
Dynamic: home-page
Dynamic: requires-dist
Dynamic: summary
